dystemctl/__init__.py
dystemctl/__main__.py
dystemctl/config.py
dystemctl/launchctl.py
dystemctl/logs.py
dystemctl/models.py
dystemctl/paths.py
dystemctl/registry.py
dystemctl/systemd.py
dystemctl/utils.py
dystemctl/cli/__init__.py
dystemctl/cli/app.py
dystemctl/cli/control.py
dystemctl/cli/info.py
dystemctl/cli/journal.py
dystemctl/cli/run.py
dystemctl/cli/system.py
dystemctl/cli/units.py
dystemctl-0.1.1.dist-info/METADATA
dystemctl-0.1.1.dist-info/WHEEL
dystemctl-0.1.1.dist-info/entry_points.txt
dystemctl-0.1.1.dist-info/licenses/LICENSE
dystemctl-0.1.1.dist-info/RECORD
