Metadata-Version: 2.4
Name: dystemctl
Version: 0.1.1
Summary: systemd emulation for Darwin - provides systemctl/journalctl on macOS
Author: sielicki
License: MIT
License-File: LICENSE
Keywords: darwin,journalctl,launchd,macos,systemctl,systemd
Classifier: Development Status :: 4 - Beta
Classifier: Environment :: Console
Classifier: Intended Audience :: Developers
Classifier: Intended Audience :: System Administrators
Classifier: License :: OSI Approved :: MIT License
Classifier: Operating System :: MacOS
Classifier: Programming Language :: Python :: 3
Classifier: Programming Language :: Python :: 3.12
Classifier: Programming Language :: Python :: 3.13
Classifier: Topic :: System :: Systems Administration
Classifier: Topic :: Utilities
Requires-Python: >=3.12
Requires-Dist: rich>=13.0.0
Requires-Dist: shellingham>=1.5.0
Requires-Dist: typer>=0.9.0
